{
  "$schema": "http://json-schema.org/draft-07/schema#",
  "title": "UI Kit Additional Foundations",
  "description": "Branding assets and spacing/grid systems",
  "version": "1.0.0",
  "extractedDate": "2025-10-24",
  "branding": {
    "name": "Brand Assets",
    "pageId": "15:336",
    "description": "Logo variations and brand identity assets",
    "logos": {
      "primary": {
        "name": "Logo (Full)",
        "componentId": "4616:521",
        "description": "Full horizontal logo with icon and wordmark",
        "variations": ["Color", "White", "Black"],
        "fileFormats": ["SVG (vector)", "PNG @1x/2x/3x"],
        "minWidth": 120,
        "clearSpace": "Minimum padding of logo height × 0.25"
      },
      "short": {
        "name": "Logo - Short",
        "componentId": "4616:16825",
        "description": "Icon-only logo mark",
        "variations": ["Color", "White", "Black"],
        "sizes": ["24×24", "32×32", "48×48"],
        "usage": ["Mobile headers", "Favicons", "App icons"]
      },
      "vertical": {
        "name": "Vertical Logo",
        "dimensions": "1000×1000",
        "description": "Stacked logo with icon above wordmark",
        "usage": ["Square containers", "Social media profiles"]
      },
      "horizontal": {
        "name": "Horizontal Logo",
        "aspectRatio": "2:1",
        "description": "Wide horizontal logo format",
        "usage": ["Headers", "Email signatures", "Marketing materials"]
      }
    },
    "brandColors": {
      "primary": "#25ECFF",
      "secondary": "#C6FF77",
      "dark": "#1D092F",
      "purple": "#9B4DFF"
    },
    "usage": {
      "doNot": [
        "Stretch or distort logo",
        "Change brand colors",
        "Add effects or shadows",
        "Rotate logo",
        "Place on busy backgrounds without proper contrast"
      ],
      "do": [
        "Maintain aspect ratio",
        "Provide adequate clear space",
        "Use approved color variations",
        "Ensure legibility at all sizes",
        "Use high-resolution assets"
      ]
    }
  },
  "spacingAndGrids": {
    "name": "Layout System",
    "pageId": "20:336",
    "description": "Grid systems, breakpoints, and spacing standards",
    "gridSystem": {
      "desktop": {
        "columns": 12,
        "gutter": 24,
        "margin": 64,
        "maxWidth": 1200
      },
      "tablet": {
        "columns": 8,
        "gutter": 20,
        "margin": 32,
        "maxWidth": 768
      },
      "mobile": {
        "columns": 4,
        "gutter": 16,
        "margin": 16,
        "maxWidth": 390
      }
    },
    "breakpoints": {
      "xs": {
        "range": "0-479px",
        "description": "Small mobile devices"
      },
      "sm": {
        "range": "480-767px",
        "description": "Mobile devices"
      },
      "md": {
        "range": "768-1023px",
        "description": "Tablets"
      },
      "lg": {
        "range": "1024-1439px",
        "description": "Desktop"
      },
      "xl": {
        "range": "1440px+",
        "description": "Large desktop"
      }
    },
    "spacingScale": {
      "reference": "See spacing.json for complete 8pt grid system",
      "values": [0, 2, 4, 8, 12, 16, 24, 32, 48, 64, 80, 96, 128],
      "usage": "All spacing (padding, margins, gaps) must align to 8pt grid"
    }
  },
  "recreationGuide": {
    "logo": "// Import logo as image or recreate as SVG path; const logo = create_rectangle_with_image_fill({ imageUrl: 'logo-url', width: 160, height: 32 }); // OR use create_path for vector recreation",
    "grid": "// Apply layout grid to frames; add_layout_grid({ nodeId: frameId, pattern: 'COLUMNS', count: 12, gutter: 24, margin: 64 });"
  },
  "_extraction_notes": {
    "methodology": "Assets extracted from Figma pages 'Branding' (ID: 15:336) and 'Spacing & Grids' (ID: 20:336)",
    "status": "COMPLETE - Brand assets and grid systems documented"
  }
}
